lifetables/__init__.py
lifetables/arriaga.py
lifetables/helpers.py
lifetables/life_table.py
lifetables/mortality_rates.py
lifetables/populations.py
lifetables/data/__init__.py
lifetables/data/hmd/bltper_1x1.txt
lifetables/data/hmd/fltper_1x1.txt
lifetables/data/hmd/mltper_1x1.txt
lifetables-0.0.11.dist-info/METADATA
lifetables-0.0.11.dist-info/WHEEL
lifetables-0.0.11.dist-info/licenses/LICENSE
lifetables-0.0.11.dist-info/RECORD
