Metadata-Version: 2.4
Name: lifetables
Version: 0.0.11
Summary: Life tables in Python
Project-URL: Homepage, https://github.com/alipatti/lifetables
Author-email: Alistair Pattison <alistairpattison@gmail.com>
License-Expression: MIT
License-File: LICENSE
Classifier: Operating System :: OS Independent
Classifier: Programming Language :: Python :: 3
Requires-Python: >=3.9
Requires-Dist: joblib>=1.4.2
Requires-Dist: lxml>=5.3.1
Requires-Dist: pandas>=2.0.3
Requires-Dist: polars-utils>=0.1.6
Requires-Dist: polars>=1.8.2
Requires-Dist: rich>=13.9.4
